projen_test/__init__.py
projen_test/py.typed
projen_test/_jsii/__init__.py
projen_test/_jsii/projen-test@0.1.109.jsii.tgz
projen_test-0.1.109.dist-info/LICENSE
projen_test-0.1.109.dist-info/METADATA
projen_test-0.1.109.dist-info/WHEEL
projen_test-0.1.109.dist-info/top_level.txt
projen_test-0.1.109.dist-info/RECORD
